ttp/__init__.py
ttp/main.py
ttp/templates/default.md
time_tracker_plus-1.1.dist-info/LICENSE
time_tracker_plus-1.1.dist-info/METADATA
time_tracker_plus-1.1.dist-info/WHEEL
time_tracker_plus-1.1.dist-info/entry_points.txt
time_tracker_plus-1.1.dist-info/top_level.txt
time_tracker_plus-1.1.dist-info/RECORD
