Metadata-Version: 2.1
Name: time-tracker-plus
Version: 1.1
Summary: UNKNOWN
Home-page: https://github.com/traverseda/ttp
Author: Alex Davies
Author-email: traverse.da@gmail.com
License: MIT
Download-URL: https://github.com/traverseda/ttp/archive/v1.0.tar.gz
Platform: UNKNOWN
Requires-Dist: appdirs
Requires-Dist: click
Requires-Dist: arrow
Requires-Dist: dateparser
Requires-Dist: jinja2
Requires-Dist: pygments
